{
  "name": "Фактура / 78",
  "legalName": "[УТОЧНИТЬ: ИП Фамилия И.О.]",
  "description": "Ремонт и уход за обувью, сумками и кожаными изделиями в Санкт-Петербурге",
  "url": "https://factura78.ru",
  "phone": "+7 (981) 989-00-58",
  "email": "clean_homespb@bk.ru",
  "address": {
    "street": "Московский проспект 4",
    "city": "Санкт-Петербург",
    "region": "Санкт-Петербург",
    "postalCode": "190031",
    "country": "RU"
  },
  "geo": {
    "lat": 59.925197,
    "lng": 30.318232
  },
  "openingHours": [
    { "days": "Mo-Fr", "opens": "10:00", "closes": "20:00" },
    { "days": "Sa", "opens": "11:00", "closes": "18:00" },
    { "days": "Su", "opens": "closed", "closes": "closed" }
  ],
  "social": {
    "whatsapp": "https://wa.me/79819890058",
    "telegram": "https://t.me/APEX01",
    "vk": "https://vk.com/aversal1"
  },
  "reviews": {
    "yandex": { "url": "https://yandex.com/maps/-/CPvkJ83w", "rating": 5.0 },
    "twogis": { "url": "https://go.2gis.com/rPNwS", "rating": 5.0 },
    "avito": { "url": "https://www.avito.ru/brands/i182115338/all?sellerId=a4420a45d25210d2362984b706975273", "rating": 5.0 }
  },
  "priceRange": "₽₽"
}
